czone/__init__.py
czone/generator/__init__.py
czone/generator/amorphous_algorithms.py
czone/generator/generator.py
czone/molecule/__init__.py
czone/molecule/molecule.py
czone/prefab/__init__.py
czone/prefab/prefab.py
czone/prefab/wulff.py
czone/scene/__init__.py
czone/scene/scene.py
czone/surface/__init__.py
czone/surface/adsorbate.py
czone/surface/alpha_shape.py
czone/transform/__init__.py
czone/transform/post.py
czone/transform/strain.py
czone/transform/transform.py
czone/util/__init__.py
czone/util/measure.py
czone/util/misc.py
czone/viz/__init__.py
czone/viz/viz.py
czone/volume/__init__.py
czone/volume/algebraic.py
czone/volume/volume.py
czone/volume/voxel.py
czone-2022.9.20.dist-info/LICENSE.txt
czone-2022.9.20.dist-info/METADATA
czone-2022.9.20.dist-info/WHEEL
czone-2022.9.20.dist-info/top_level.txt
czone-2022.9.20.dist-info/RECORD
