Metadata-Version: 2.1
Name: czone
Version: 2022.9.20
Summary: An open source python package for generating nanoscale+ atomic scenes
Home-page: https://github.com/lerandc/construction_zone
Author: Luis Rangel DaCosta
Author-email: luisrd@berkeley.edu
Requires-Python: >=3.7
License-File: LICENSE.txt
Requires-Dist: pymatgen (>=2022.x.x)
Requires-Dist: numpy (>=1.16.2)
Requires-Dist: scipy (>=1.3.0)
Requires-Dist: ase (>=3.21.0)
Requires-Dist: wulffpack (>=1.1.0)
